langchain_aimlapi/__init__.py
langchain_aimlapi/chat_models.py
langchain_aimlapi/constants.py
langchain_aimlapi/embeddings.py
langchain_aimlapi/image_models.py
langchain_aimlapi/llms.py
langchain_aimlapi/py.typed
langchain_aimlapi/video_models.py
langchain_aimlapi-0.1.0.dist-info/LICENSE
langchain_aimlapi-0.1.0.dist-info/METADATA
langchain_aimlapi-0.1.0.dist-info/WHEEL
langchain_aimlapi-0.1.0.dist-info/RECORD
