Metadata-Version: 2.3
Name: langchain-aimlapi
Version: 0.1.0
Summary: An integration package connecting Aimlapi and LangChain
License: MIT
Author: Dmitry Tumanov
Author-email: d1m7asis@gmail.com
Requires-Python: >=3.9,<4.0
Classifier: License :: OSI Approved :: MIT License
Classifier: Programming Language :: Python :: 3
Classifier: Programming Language :: Python :: 3.9
Classifier: Programming Language :: Python :: 3.10
Classifier: Programming Language :: Python :: 3.11
Classifier: Programming Language :: Python :: 3.12
Classifier: Programming Language :: Python :: 3.13
Requires-Dist: aiohttp (>=3.9.1,<4.0.0)
Requires-Dist: langchain-core (>=0.3.15,<0.4.0)
Requires-Dist: langchain-openai (>=0.3,<0.4)
Requires-Dist: requests (>=2,<3)
Project-URL: Repository, https://github.com/langchain-ai/langchain
Project-URL: Release Notes, https://github.com/langchain-ai/langchain/releases?q=tag%3A%22aimlapi%3D%3D0%22&expanded=true
Project-URL: Source Code, https://github.com/langchain-ai/langchain/tree/master/libs/partners/aimlapi
